py_singl_slider/__init__.py
py_singl_slider/theme/one/bar_center.png
py_singl_slider/theme/one/bar_corner.png
py_singl_slider/theme/one/handler.png
py_singl_slider/theme/two/bar_center.png
py_singl_slider/theme/two/bar_corner.png
py_singl_slider/theme/two/handler.png
py_singl_slider-1.0.7.dist-info/METADATA
py_singl_slider-1.0.7.dist-info/WHEEL
py_singl_slider-1.0.7.dist-info/entry_points.txt
py_singl_slider-1.0.7.dist-info/top_level.txt
py_singl_slider-1.0.7.dist-info/RECORD
