Metadata-Version: 2.1
Name: py-singl-slider
Version: 1.0.7
Summary: A single virtual slider control
Home-page: https://github.com/kerodekroma/py-singl-slider
Author: kerodekroma
Author-email: kerodekroma@gmail.com
License: UNKNOWN
Platform: UNKNOWN
Classifier: Programming Language :: Python :: 3
Classifier: License :: OSI Approved :: MIT License
Classifier: Operating System :: OS Independent
Requires-Python: >=3.6
Requires-Dist: pygame (>=2.0.0)
